setup.py
django_rrd.egg-info/PKG-INFO
django_rrd.egg-info/SOURCES.txt
django_rrd.egg-info/dependency_links.txt
django_rrd.egg-info/requires.txt
django_rrd.egg-info/top_level.txt
djangorrd/__init__.py
djangorrd/admin.py
djangorrd/config.py
djangorrd/models.py
djangorrd/urls.py
djangorrd/views.py
djangorrd/management/__init__.py
djangorrd/management/commands/__init__.py
djangorrd/management/commands/rrd_poller.py
djangorrd/migrations/0001_initial.py
djangorrd/migrations/0002_auto_20151010_1834.py
djangorrd/migrations/0003_auto_20151010_2128.py
djangorrd/migrations/0004_auto_20151104_1439.py
djangorrd/migrations/__init__.py
djangorrd/tests/__init__.py
djangorrd/tests/test_models.py