Metadata-Version: 1.1
Name: django-rrd
Version: 0.0.10
Summary: Web frontend to RRDtool based on Django
Home-page: https://sourceforge.net/p/django-rrd/wiki/
Author: Okami
Author-email: okami@fuzetsu.info
License: GPLv3
Keywords: django rrd rrdtool
Platform: UNKNOWN
Classifier: Development Status :: 3 - Alpha
Classifier: Programming Language :: Python :: 3
Classifier: License :: OSI Approved :: GNU General Public License v3 or later (GPLv3+)
Classifier: Framework :: Django
